LICENSE
abstract_codebase/__init__.py
abstract_codebase/accreditation.py
abstract_codebase/directories.py
abstract_codebase/metacoding.py
abstract_codebase/registration.py
abstract_codebase/tools.py
abstract_codebase/typescripts.py
abstract_codebase-0.1.1.dist-info/LICENSE
abstract_codebase-0.1.1.dist-info/WHEEL
abstract_codebase-0.1.1.dist-info/METADATA
abstract_codebase-0.1.1.dist-info/RECORD
