Metadata-Version: 2.1
Name: abstract-codebase
Version: 0.1.1
Summary: Abstract codebase with utilities to register generic modules.
Home-page: https://github.com/aidd-msca/abstract-codebase
License: MIT
Keywords: codebase,module registry,accreditation system
Author: Peter Hartog
Author-email: peter.hartog@hotmail.nl
Requires-Python: >=3.8,<4.0
Classifier: Development Status :: 2 - Pre-Alpha
Classifier: Environment :: GPU :: NVIDIA CUDA :: 11.4
Classifier: License :: OSI Approved :: MIT License
Classifier: Programming Language :: Python :: 3
Classifier: Programming Language :: Python :: 3.10
Classifier: Programming Language :: Python :: 3.8
Classifier: Programming Language :: Python :: 3.9
Classifier: Topic :: Scientific/Engineering :: Artificial Intelligence
Project-URL: Repository, https://github.com/aidd-msca/abstract-codebase
